{
  "kind": "collectionType",
  "collectionName": "plcs",
  "info": {
    "singularName": "plc",
    "pluralName": "plcs",
    "displayName": "plc"
  },
  "options": {
    "draftAndPublish": true
  },
  "pluginOptions": {},
  "attributes": {
    "name": {
      "type": "string",
      "required": true
    },
    "ip_address": {
      "type": "string",
      "required": true
    },
    "rack": {
      "type": "integer",
      "default": 0
    },
    "slot": {
      "type": "integer",
      "default": 0
    },
    "active": {
      "type": "boolean",
      "default": true
    },
    "needs_reload": {
      "type": "boolean",
      "default": false
    },
    "users_permissions_user": {
      "type": "relation",
      "relation": "manyToOne",
      "target": "plugin::users-permissions.user",
      "inversedBy": "plcs"
    },
    "tags": {
      "type": "relation",
      "relation": "oneToMany",
      "target": "api::tag.tag",
      "mappedBy": "plc_device"
    }
  }
}